[
  {
    "id": 1,
    "title": "Spotify 3 mån för 0 kr (nya användare)",
    "price": "0 kr",
    "merchant": "Spotify",
    "url": "https://example.com/aff/spotify",
    "image": "/logo.svg",
    "tags": [
      "musik",
      "kampanj"
    ],
    "featured": true
  },
  {
    "id": 2,
    "title": "Amazon: -30% på utvalda gamingheadsets",
    "price": "Variabel",
    "merchant": "Amazon",
    "url": "https://example.com/aff/amazon-headset",
    "image": "/logo.svg",
    "tags": [
      "gaming",
      "ljud"
    ],
    "featured": false
  }
]